laniakea_plugin_sdk/__init__.py
laniakea_plugin_sdk/controller.py
laniakea_plugin_sdk/datasource.py
laniakea_plugin_sdk/proto/__init__.py
laniakea_plugin_sdk/proto/plugin_pb2.py
laniakea_plugin_sdk/proto/plugin_pb2_grpc.py
laniakea_plugin_sdk-1.0.15.dist-info/LICENSE
laniakea_plugin_sdk-1.0.15.dist-info/METADATA
laniakea_plugin_sdk-1.0.15.dist-info/WHEEL
laniakea_plugin_sdk-1.0.15.dist-info/top_level.txt
laniakea_plugin_sdk-1.0.15.dist-info/RECORD
