Metadata-Version: 2.1
Name: laniakea-plugin-sdk
Version: 1.0.15
Summary: The python plugin SDK for Laniakea
Author-email: Paul Côté <paul.cote@sssoc.ca>
License: MIT License        
Project-URL: Homepage, https://github.com/SSSOC-CAN/laniakea-plugin-sdk
Project-URL: Bug Tracker, https://github.com/SSSOC-CAN/laniakea-plugin-sdk/issues
Classifier: Programming Language :: Python :: 3
Classifier: License :: OSI Approved :: MIT License
Classifier: Operating System :: OS Independent
Requires-Python: >=3.7
License-File: LICENSE
